autocare_dlt/__init__.py
autocare_dlt/core/__init__.py
autocare_dlt/core/dataset/__init__.py
autocare_dlt/core/dataset/coco_base_dataset.py
autocare_dlt/core/dataset/coco_classification_dataset.py
autocare_dlt/core/dataset/coco_detection_dataset.py
autocare_dlt/core/dataset/coco_pose_dataset.py
autocare_dlt/core/dataset/coco_segmentation_dataset.py
autocare_dlt/core/dataset/coco_text_recognition_dataset.py
autocare_dlt/core/dataset/utils/__init__.py
autocare_dlt/core/dataset/utils/builder.py
autocare_dlt/core/dataset/utils/classification_eval.py
autocare_dlt/core/dataset/utils/coco_eval.py
autocare_dlt/core/dataset/utils/functions.py
autocare_dlt/core/dataset/utils/pose_eval.py
autocare_dlt/core/dataset/utils/regression_eval.py
autocare_dlt/core/dataset/utils/seg_eval.py
autocare_dlt/core/dataset/utils/text_recognition_eval.py
autocare_dlt/core/dataset/utils/transforms.py
autocare_dlt/core/loss/__init__.py
autocare_dlt/core/loss/class_balance_loss.py
autocare_dlt/core/loss/ctc_loss.py
autocare_dlt/core/loss/focal_loss.py
autocare_dlt/core/loss/iou_loss.py
autocare_dlt/core/loss/loss_manager.py
autocare_dlt/core/loss/lpr_loss.py
autocare_dlt/core/loss/pose_loss.py
autocare_dlt/core/loss/retinanet_loss.py
autocare_dlt/core/loss/seg_loss.py
autocare_dlt/core/loss/ssd4point_loss.py
autocare_dlt/core/loss/ssd_loss.py
autocare_dlt/core/loss/yolo_loss.py
autocare_dlt/core/model/__init__.py
autocare_dlt/core/model/backbone/UNet_backbone.py
autocare_dlt/core/model/backbone/VGG_16_backbone.py
autocare_dlt/core/model/backbone/__init__.py
autocare_dlt/core/model/backbone/yolov5_backbone.py
autocare_dlt/core/model/classifier/__init__.py
autocare_dlt/core/model/classifier/base_classifier.py
autocare_dlt/core/model/classifier/classifier.py
autocare_dlt/core/model/detector/__init__.py
autocare_dlt/core/model/detector/base_detector.py
autocare_dlt/core/model/detector/retinanet.py
autocare_dlt/core/model/detector/ssd.py
autocare_dlt/core/model/detector/yolov5.py
autocare_dlt-0.2.6.dist-info/LICENSE
autocare_dlt-0.2.6.dist-info/METADATA
autocare_dlt-0.2.6.dist-info/WHEEL
autocare_dlt-0.2.6.dist-info/top_level.txt
autocare_dlt-0.2.6.dist-info/RECORD
