Metadata-Version: 2.1
Name: autocare-dlt
Version: 0.2.6
Summary: Autocare Tx Model
Home-page: https://github.com/snuailab/autocare_dlt
Author: SNUAILAB
Author-email: jaeseung.lim@snuailab.ai
License: GPL-3.0
Project-URL: Bug Reports, https://github.com/snuailab/autocare_dlt/issues
Project-URL: Source, https://github.com/snuailab/autocare_dlt
Keywords: machine-learning,deep-learning,vision,ML,DL,AI,YOLO,SNUAILAB
Classifier: Development Status :: 3 - Alpha
Classifier: Intended Audience :: Developers
Classifier: Intended Audience :: Science/Research
Classifier: License :: OSI Approved :: GNU General Public License v3 (GPLv3)
Classifier: Programming Language :: Python :: 3.9
Classifier: Topic :: Software Development
Classifier: Topic :: Scientific/Engineering
Classifier: Topic :: Scientific/Engineering :: Artificial Intelligence
Classifier: Topic :: Scientific/Engineering :: Image Recognition
Classifier: Operating System :: POSIX :: Linux
Requires-Python: >=3.9
License-File: LICENSE
Requires-Dist: timm >=0.6.1
Requires-Dist: numpy >=1.23.1
Requires-Dist: opencv-python >=4.6.0.66
Requires-Dist: loguru >=0.6.0
Requires-Dist: scikit-image >=0.19.3
Requires-Dist: tqdm >=4.64.1
Requires-Dist: Pillow >=9.2.0
Requires-Dist: thop >=0.1.1.post2209072238
Requires-Dist: ninja >=1.10.2.4
Requires-Dist: tabulate >=0.8.10
Requires-Dist: tensorboard >=2.10.1
Requires-Dist: python-box >=7.0.1
Requires-Dist: pytest-cov >=4.0.0
Requires-Dist: albumentations >=1.1.0
Requires-Dist: nltk >=3.7
Requires-Dist: lmdb >=1.3.0
Requires-Dist: natsort >=8.2.0
Requires-Dist: torchinfo >=1.7.0
Requires-Dist: pandas >=1.5.0
Requires-Dist: optuna >=3.0.3
Requires-Dist: pycocotools >=2.0.2
Requires-Dist: onnx >=1.12.0
Requires-Dist: onnxruntime >=1.11.1
Requires-Dist: onnx-simplifier >=0.4.0
Requires-Dist: sentry-sdk
